Metadata-Version: 1.1
Name: makeauto
Version: 0.1.3
Summary: Run make automatically on sources change.
Home-page: https://github.com/gchlebus/makeauto
Author: Grzegorz Chlebus
Author-email: gchlebus@gmail.com
License: BSD 3-Clause
Keywords: make makefile
Platform: UNKNOWN
Classifier: Development Status :: 4 - Beta
Classifier: Topic :: Utilities
Classifier: Programming Language :: Python
Classifier: License :: OSI Approved :: BSD License
